LICENSE
MANIFEST.in
README.rst
setup.py
django_janus.egg-info/PKG-INFO
django_janus.egg-info/SOURCES.txt
django_janus.egg-info/dependency_links.txt
django_janus.egg-info/requires.txt
django_janus.egg-info/top_level.txt
janus/__init__.py
janus/adapter.py
janus/provider.py
janus/urls.py
janus/views.py
janus/templates/registration/call-admin.html
janus/templates/registration/login.html
janus/templates/registration/redirect-login.html